fastwebhook/__init__.py
fastwebhook/_nbdev.py
fastwebhook/core.py
fastwebhook-0.0.15.dist-info/LICENSE
fastwebhook-0.0.15.dist-info/METADATA
fastwebhook-0.0.15.dist-info/WHEEL
fastwebhook-0.0.15.dist-info/entry_points.txt
fastwebhook-0.0.15.dist-info/top_level.txt
fastwebhook-0.0.15.dist-info/RECORD
