Metadata-Version: 2.1
Name: fastwebhook
Version: 0.0.15
Summary: A simple GitHub webhook server
Home-page: https://github.com/fastai/fastwebhook/tree/master/
Author: Jeremy Howard
Author-email: info@fast.ai
License: Apache Software License 2.0
Keywords: github webhook python nbdev
Platform: UNKNOWN
Classifier: Development Status :: 3 - Alpha
Classifier: Intended Audience :: Developers
Classifier: License :: OSI Approved :: Apache Software License
Classifier: Natural Language :: English
Classifier: Programming Language :: Python :: 3.6
Classifier: Programming Language :: Python :: 3.7
Classifier: Programming Language :: Python :: 3.8
Requires-Python: >=3.6
License-File: LICENSE
Requires-Dist: pip
Requires-Dist: packaging
Requires-Dist: fastcore (>=1.0.17)
Requires-Dist: fastcgi
Requires-Dist: ghapi
Requires-Dist: tweepy
Provides-Extra: dev
